campaignData/locRef.py
campaignData/rawDash.py
campaignData/__init__.py
campaignData-0.0.1.dist-info/DESCRIPTION.rst
campaignData-0.0.1.dist-info/METADATA
campaignData-0.0.1.dist-info/metadata.json
campaignData-0.0.1.dist-info/RECORD
campaignData-0.0.1.dist-info/top_level.txt
campaignData-0.0.1.dist-info/WHEEL
